data_memory.v
module data_memory (
    input  wire        clk,
    input  wire        mem_write,
    input  wire        mem_read,
    input  wire [31:0] address,    // Endereço calculado pela ALU
    input  wire [31:0] write_data, // Dado a ser escrito (vem de rt)
    output wire [31:0] read_data   // Dado lido (vai para o mux de writeback)
);

    // Memória de 256 palavras
    reg [31:0] memory [0:255];
    
    integer i;
    initial begin
        for (i=0; i<256; i=i+1) memory[i] = 32'b0; // Limpa a memória
    end

    // Leitura Combinacional
    // Se MemRead estiver ativo, lê da memória. Caso contrário, retorna 0.
    assign read_data = (mem_read) ? memory[address[9:2]] : 32'b0;

    // Escrita Síncrona
    always @(posedge clk) begin
        if (mem_write) begin
            memory[address[9:2]] <= write_data;
        end
    end

endmodule

alu.v
module alu(
    input  wire [31:0] a,
    input  wire [31:0] b,
    input  wire [3:0]  alu_ctrl,
    input  wire [4:0]  shamt,
    output reg  [31:0] result,
    output wire        zero,
    output reg         carry_out,
    output reg         overflow
);

    // Fio auxiliar para capturar o carry (33 bits para pegar o bit extra)
    wire [32:0] sum_extended;
    wire [32:0] sub_extended;

    // Cálculos auxiliares para carry e overflow
    assign sum_extended = {1'b0, a} + {1'b0, b};
    assign sub_extended = {1'b0, a} - {1'b0, b};

    always @(*) begin
        // Valores padrão para evitar latches
        result    = 32'd0;
        carry_out = 1'b0;
        overflow  = 1'b0;

        case (alu_ctrl)
            4'b0000: result = a & b;           // AND
            4'b0001: result = a | b;           // OR

            4'b0010: begin                    // ADD
                result    = a + b;
                carry_out = sum_extended[32];
                // Overflow: sinais iguais somados resultam em sinal diferente
                overflow  = (~(a[31] ^ b[31])) & (a[31] ^ result[31]);
            end

            4'b0011: result = b << shamt; // SLL (shift left logical)
            4'b0100: result = b >> shamt; // SRL
            
            4'b0110: begin                    // SUB
                result    = a - b;
                carry_out = sub_extended[32];
                // Overflow: sinais diferentes subtraídos, resultado difere do minuendo
                overflow  = (a[31] ^ b[31]) & (a[31] ^ result[31]);
            end

            4'b0111: result = ($signed(a) < $signed(b)) ? 32'd1 : 32'd0; // SLT
            4'b1100: result = ~(a | b);        // NOR
            
            default: result = 32'd0;
        endcase
    end

    assign zero = (result == 32'd0);

endmodule

alu_control.v
module alu_control (
    input  wire [1:0] alu_op,      // Vem da Control Unit
    input  wire [5:0] funct,       // Vem da Instrução [5:0]
    output reg  [3:0] alu_ctrl     // Vai para a sua alu_32
);

    always @(*) begin
        // Valor padrão para evitar latches
        alu_ctrl = 4'b0000;

        case (alu_op)
            2'b00: alu_ctrl = 4'b0010; // LW/SW -> Soma (ADD)
            2'b01: alu_ctrl = 4'b0110; // BEQ   -> Subtração (SUB)
            2'b10: begin               // Tipo-R -> Olha o Funct
                case (funct)
                    6'b000000: alu_ctrl = 4'b0011; // SLL
                    6'b000010: alu_ctrl = 4'b0100; // SRL
                    6'b100000: alu_ctrl = 4'b0010; // ADD
                    6'b100010: alu_ctrl = 4'b0110; // SUB
                    6'b100100: alu_ctrl = 4'b0000; // AND
                    6'b100101: alu_ctrl = 4'b0001; // OR
                    6'b101010: alu_ctrl = 4'b0111; // SLT
                    6'b100111: alu_ctrl = 4'b1100; // NOR
                    default:   alu_ctrl = 4'b0000; 
                endcase
            end
            default: alu_ctrl = 4'b0000;
        endcase
    end
endmodule

registers.v
module registers(
	input clk,
	input write_en,
	input [4:0] read_address1, read_address2, write_reg,
	input [31:0] write_data,
	output [31:0] read_data1, read_data2
);
	reg [31:0] registers [31:0];

	integer i;
	initial begin
		for (i = 0; i < 32; i = i + 1) begin
            registers[i] = 32'b0;
        end
    end

	always @(posedge clk) begin
		if (write_en) begin
		if (write_reg != 5'b0) begin
		registers[write_reg] <= write_data;
		end
	end
	end

	assign read_data1 = (read_address1==5'b0) ? 32'b0 : registers[read_address1];
	assign read_data2 = (read_address2==5'b0) ? 32'b0 : registers[read_address2];
endmodule

cu.v
module cu (
    input  wire [5:0] opcode,
    output reg        reg_dst,
    output reg        alu_src,
    output reg        mem_to_reg,
    output reg        reg_write,
    output reg        mem_read,
    output reg        mem_write,
    output reg        branch,
    output reg  [1:0] alu_op
);

    always @(*) begin
        // Valores padrão (Default) para evitar latches
        reg_dst    = 0; alu_src    = 0; mem_to_reg = 0;
        reg_write  = 0; mem_read   = 0; mem_write  = 0;
        branch     = 0; alu_op     = 2'b00;

        case (opcode)
            6'b000000: begin // TIPO R (add, sub, and, or, slt, nor)
                reg_dst    = 1;
                reg_write  = 1;
                alu_op     = 2'b10;
            end
            6'b100011: begin // LW
                alu_src    = 1;
                mem_to_reg = 1;
                reg_write  = 1;
                mem_read   = 1;
                alu_op     = 2'b00;
            end
            6'b101011: begin // SW
                alu_src    = 1;
                mem_write  = 1;
                alu_op     = 2'b00;
            end
            6'b000100: begin // BEQ
                branch     = 1;
                alu_op     = 2'b01;
            end
            default: begin
                // Opcode desconhecido
            end
        endcase
    end

endmodule

instruction_memory.v
module instruction_memory (
    input  wire [31:0] address, //endereco de PC
    output reg  [31:0] instruction
);

    reg [31:0] memory [0:255]; 

    initial begin
        $readmemb("program.bin", memory);
    end


    //LEITURA COMBINACIONAL
    always @(*) begin
        instruction = memory[address[9:2]]; 
    end

endmodule

top.v
module top (
    input wire clk,
    input wire reset
);

    // ==========================================
    // 1. DECLARAÇÃO DOS FIOS (INTERCONEXÕES)
    // ==========================================
    
    // PC e Instrução
    reg  [31:0] pc;
    wire [31:0] pc_next, pc_plus4, pc_branch;
    wire [31:0] instruction;

    wire [4:0] shamt;

    // Sinais de Controle (Saídas da Unidade de Controle)
    wire reg_dst, branch, mem_read, mem_to_reg;
    wire [1:0] alu_op;
    wire mem_write, alu_src, reg_write;

    // Banco de Registradores
    wire [31:0] read_data1, read_data2;
    wire [31:0] write_data;      // Dado que volta para ser escrito
    wire [4:0]  write_reg_addr;  // Endereço de escrita escolhido (rd ou rt)

    // ALU e Extensão de Sinal
    wire [31:0] sign_ext_imm;
    wire [31:0] alu_input_b;
    wire [31:0] alu_result;
    wire [3:0]  alu_control_sig;
    wire zero_flag;

    // Memória de Dados
    wire [31:0] mem_read_data;

    //jal
    wire op_jal  = (instruction[31:26] == 6'b000011);
    wire op_j    = (instruction[31:26] == 6'b000010);
    wire is_jump = op_jal | op_j;

    // Lógica de Branch
    wire pc_src; // Decide se pula ou não (Branch & Zero)

    // ==========================================
    // 2. ESTÁGIO DE BUSCA (FETCH)
    // ==========================================

    wire is_jr = (instruction[31:26] == 6'b000000) && (instruction[5:0] == 6'b001000);

    
    // Lógica do PC 
    always @(posedge clk or posedge reset) begin
        if (reset)
            pc <= 32'b0;
        else
            pc <= pc_next;
    end

    // Somador simples (PC + 4)
    assign pc_plus4 = pc + 4;

    // Memória de Instruções 
    instruction_memory imem (
        .address(pc),
        .instruction(instruction)
    );

    // ==========================================
    // 3. ESTÁGIO DE DECODIFICAÇÃO E CONTROLE
    // ==========================================

    wire [31:0] jump_addr = {pc_plus4[31:28], instruction[25:0], 2'b00};
    assign shamt = instruction[10:6];

    // Unidade de Controle Principal
    cu control_unit (
        .opcode(instruction[31:26]),
        .reg_dst(reg_dst),
        .alu_src(alu_src),
        .mem_to_reg(mem_to_reg),
        .reg_write(reg_write),
        .mem_read(mem_read),
        .mem_write(mem_write),
        .branch(branch),
        .alu_op(alu_op)
    );

    // Multiplexador para definir onde escrever (rt ou rd?) e com suporte pro JAL, escreve no reg 31
    // Se RegDst=0 -> rt (bits 20-16), Se RegDst=1 -> rd (bits 15-11)
    assign write_reg_addr = (op_jal) ? 5'd31 : 
                            ((reg_dst) ? instruction[15:11] : instruction[20:16]);
    // Banco de Registradores
    registers reg_file (
        .clk(clk),
        .write_en((reg_write & ~is_jr) | op_jal),
        .read_address1(instruction[25:21]), // rs
        .read_address2(instruction[20:16]), // rt
        .write_reg(write_reg_addr),
        .write_data(write_data),
        .read_data1(read_data1),
        .read_data2(read_data2)
    );

    // Extensão de Sinal (16 bits -> 32 bits)
    // Pega o bit 15 (sinal) e repete 16 vezes, concatenando com o imediato original
    assign sign_ext_imm = {{16{instruction[15]}}, instruction[15:0]};

    // ==========================================
    // 4. ESTÁGIO DE EXECUÇÃO
    // ==========================================

    // Unidade de Controle da ALU (Gera os 4 bits de controle)
    alu_control alu_ctrl_unit (
        .alu_op(alu_op),
        .funct(instruction[5:0]),
        .alu_ctrl(alu_control_sig)
    );

    // Multiplexador da ALU (ALUSrc)
    // O segundo operando é o registrador (0) ou o imediato estendido (1)?
    assign alu_input_b = (alu_src) ? sign_ext_imm : read_data2;

    // A Própria ALU
    alu main_alu (
        .a(read_data1),
        .b(alu_input_b),
        .shamt(shamt),
        .alu_ctrl(alu_control_sig),
        .result(alu_result),
        .zero(zero_flag),
        .carry_out(),
        .overflow()
    );

    // ==========================================
    // 5. ESTÁGIO DE MEMÓRIA
    // ==========================================

    data_memory dmem (
        .clk(clk),
        .mem_write(mem_write),
        .mem_read(mem_read),
        .address(alu_result),
        .write_data(read_data2), // Dado a ser salvo na memória (vem de rt)
        .read_data(mem_read_data)
    );

    // ==========================================
    // 6. ESTÁGIO DE WRITE-BACK E LÓGICA DE PROX PC
    // ==========================================

    // Multiplexador de MemToReg com suporte pro JAL, escreve pc+4
    // O que volta pro registrador? Resultado da ALU (0) ou Dado da Memória (1)?
    assign write_data = (op_jal)     ? pc_plus4 :
                        ((mem_to_reg) ? mem_read_data : alu_result);

    // Lógica de Branch
    // Endereço de salto = PC+4 + (offset deslocado de 2 bits)
    assign pc_branch = pc_plus4 + (sign_ext_imm << 2);

    // Decisão do Branch: Só pula se instrução for Branch E ALU deu Zero (iguais)
    assign pc_src = branch & zero_flag;

    // Mux do PC com prioridades para JR e JAL
    assign pc_next = (is_jr)   ? read_data1 :
                 (is_jump) ? jump_addr  :
                 (pc_src)  ? pc_branch  : pc_plus4;

endmodule

testbench.v
`timescale 1ns / 1ps

module testbench;

    // Sinais para conectar no TOP
    reg clk;
    reg reset;

    // Instância do seu processador (Device Under Test)
    top dut (
        .clk(clk),
        .reset(reset)
    );

    // Fios espiões para ver a memória no GTKWave (VCD padrão)
    // Índice do Verilog = Endereço / 4
    // Endereço 4 -> Índice 1
    wire [31:0] check_size = dut.dmem.memory[0]; // Tamanho
    wire [31:0] check_val1 = dut.dmem.memory[1]; // 10 (vira 1)
    wire [31:0] check_val2 = dut.dmem.memory[2]; // 3  (vira 2)
    wire [31:0] check_val3 = dut.dmem.memory[3]; // 50 (vira 3)
    wire [31:0] check_val4 = dut.dmem.memory[4]; // 2  (vira 10)
    wire [31:0] check_val5 = dut.dmem.memory[5]; // 1  (vira 50)

    // 1. Geração de Clock (Período de 10ns)
    initial begin
        clk = 0;
        forever #5 clk = ~clk;
    end

    // 2. Sequência de Teste
    initial begin
        // Arquivo de ondas para visualizar no GTKWave
        $dumpfile("mips_waves.vcd");
        $dumpvars(0, testbench);

        // Inicialização
        reset = 1;
        #20;         // Segura o reset por 20ns
        reset = 0;   // Solta o reset (O processador começa aqui!)

        // Tempo de simulação
        // Heap Sort demora um pouco. Vamos dar 100.000ns.
        // Se não terminar, aumente este número.
        #100000;
        
        $display("Simulacao finalizada.");
        $finish;
    end

    // Monitor simples no terminal (opcional)
    // Mostra o PC e a instrução a cada ciclo positivo
    /*
    always @(posedge clk) begin
        if (!reset) begin
            $display("Time: %d, PC: %h, Instr: %h", $time, dut.pc, dut.instruction);
        end
    end
    */

endmodule

mips_waves.vcd
$date
	Sun Feb 01 14:29:29 2026
$end
$version
	Icarus Verilog
$end
$timescale
	1ps
$end
$scope module testbench $end
$var wire 32 ! check_size [31:0] $end
$var wire 32 " check_val1 [31:0] $end
$var wire 32 # check_val2 [31:0] $end
$var wire 32 $ check_val3 [31:0] $end
$var wire 32 % check_val4 [31:0] $end
$var wire 32 & check_val5 [31:0] $end
$var reg 1 ' clk $end
$var reg 1 ( reset $end
$scope module dut $end
$var wire 1 ' clk $end
$var wire 1 ) is_jr $end
$var wire 1 * is_jump $end
$var wire 1 + pc_src $end
$var wire 1 ( reset $end
$var wire 1 , zero_flag $end
$var wire 5 - write_reg_addr [4:0] $end
$var wire 32 . write_data [31:0] $end
$var wire 32 / sign_ext_imm [31:0] $end
$var wire 5 0 shamt [4:0] $end
$var wire 1 1 reg_write $end
$var wire 1 2 reg_dst $end
$var wire 32 3 read_data2 [31:0] $end
$var wire 32 4 read_data1 [31:0] $end
$var wire 32 5 pc_plus4 [31:0] $end
$var wire 32 6 pc_next [31:0] $end
$var wire 32 7 pc_branch [31:0] $end
$var wire 1 8 op_jal $end
$var wire 1 9 op_j $end
$var wire 1 : mem_write $end
$var wire 1 ; mem_to_reg $end
$var wire 32 < mem_read_data [31:0] $end
$var wire 1 = mem_read $end
$var wire 32 > jump_addr [31:0] $end
$var wire 32 ? instruction [31:0] $end
$var wire 1 @ branch $end
$var wire 1 A alu_src $end
$var wire 32 B alu_result [31:0] $end
$var wire 2 C alu_op [1:0] $end
$var wire 32 D alu_input_b [31:0] $end
$var wire 4 E alu_control_sig [3:0] $end
$var reg 32 F pc [31:0] $end
$scope module alu_ctrl_unit $end
$var wire 6 G funct [5:0] $end
$var wire 2 H alu_op [1:0] $end
$var reg 4 I alu_ctrl [3:0] $end
$upscope $end
$scope module control_unit $end
$var wire 6 J opcode [5:0] $end
$var reg 2 K alu_op [1:0] $end
$var reg 1 A alu_src $end
$var reg 1 @ branch $end
$var reg 1 = mem_read $end
$var reg 1 ; mem_to_reg $end
$var reg 1 : mem_write $end
$var reg 1 2 reg_dst $end
$var reg 1 1 reg_write $end
$upscope $end
$scope module dmem $end
$var wire 1 ' clk $end
$var wire 1 = mem_read $end
$var wire 1 : mem_write $end
$var wire 32 L write_data [31:0] $end
$var wire 32 M read_data [31:0] $end
$var wire 32 N address [31:0] $end
$var integer 32 O i [31:0] $end
$upscope $end
$scope module imem $end
$var wire 32 P address [31:0] $end
$var reg 32 Q instruction [31:0] $end
$upscope $end
$scope module main_alu $end
$var wire 4 R alu_ctrl [3:0] $end
$var wire 32 S b [31:0] $end
$var wire 5 T shamt [4:0] $end
$var wire 1 , zero $end
$var wire 33 U sum_extended [32:0] $end
$var wire 33 V sub_extended [32:0] $end
$var wire 32 W a [31:0] $end
$var reg 1 X carry_out $end
$var reg 1 Y overflow $end
$var reg 32 Z result [31:0] $end
$upscope $end
$scope module reg_file $end
$var wire 1 ' clk $end
$var wire 5 [ read_address1 [4:0] $end
$var wire 5 \ read_address2 [4:0] $end
$var wire 32 ] write_data [31:0] $end
$var wire 1 ^ write_en $end
$var wire 5 _ write_reg [4:0] $end
$var wire 32 ` read_data2 [31:0] $end
$var wire 32 a read_data1 [31:0] $end
$var integer 32 b i [31:0] $end
$upscope $end
$upscope $end
$upscope $end
$enddefinitions $end
$comment Show the parameter values. $end
$dumpall
$end
#0
$dumpvars
b100000 b
b0 a
b0 `
b11101 _
0^
b0 ]
b11101 \
b0 [
b0 Z
0Y
0X
b0 W
b0 V
b0 U
b1111 T
b0 S
b10 R
b100000000111010000001111111100 Q
b0 P
b100000000 O
b0 N
b0 M
b0 L
b0 K
b1000 J
b10 I
b0 H
b111100 G
b0 F
b10 E
b0 D
b0 C
b0 B
0A
0@
b100000000111010000001111111100 ?
b11101000000111111110000 >
0=
b0 <
0;
0:
09
08
b111111110100 7
b100 6
b100 5
b0 4
b0 3
02
01
b1111 0
b1111111100 /
b0 .
b11101 -
1,
0+
0*
0)
1(
0'
b0 &
b0 %
b0 $
b0 #
b0 "
b0 !
$end
#5000
1'
#10000
0'
#15000
1'
#20000
0'
0(
#25000
b11011 -
b11011 _
b1000 6
b10 E
b10 I
b10 R
b1 G
b1 /
b11011 \
b0 0
b0 T
b11011000000000000000100 >
b100000000110110000000000000001 ?
b100000000110110000000000000001 Q
b1100 7
b1000 5
b100 F
b100 P
1'
#30000
0'
#35000
b1000 -
b1000 _
b1100 6
b10 E
b10 I
b10 R
b101 G
b101 /
b1000 \
b1000000000000000010100 >
b100000000010000000000000000101 ?
b100000000010000000000000000101 Q
b100000 7
b1100 5
b1000 F
b1000 P
1'
#40000
0'
#45000
b10000 6
b10 E
b10 I
b10 R
1:
1A
b0 G
b0 /
b101011 J
b1000000000000000000000 >
b10101100000010000000000000000000 ?
b10101100000010000000000000000000 Q
b10000 7
b10000 5
b1100 F
b1100 P
1'
#50000
0'
#55000
b10100 6
b10 E
b10 I
b10 R
0:
0A
b1010 G
b1010 /
b1000 J
b1000000000000000101000 >
b100000000010000000000000001010 ?
b100000000010000000000000001010 Q
b111100 7
b10100 5
b10000 F
b10000 P
1'
#60000
0'
#65000
b100 .
b100 ]
0,
b100 B
b100 N
b100 Z
b100 U
b111111111111111111111111111111100 V
b100 D
b100 S
b11000 6
b10 E
b10 I
b10 R
1:
1A
b100 G
b100 /
b101011 J
b1000000000000000010000 >
b10101100000010000000000000000100 ?
b10101100000010000000000000000100 Q
b101000 7
b11000 5
b10100 F
b10100 P
1'
#70000
0'
#75000
b0 .
b0 ]
1,
b0 B
b0 N
b0 Z
b11100 6
b10 E
b10 I
b10 R
b0 U
b0 V
b0 D
b0 S
0:
0A
b11 G
b11 /
b1000 J
b1000000000000000001100 >
b100000000010000000000000000011 ?
b100000000010000000000000000011 Q
b101000 7
b11100 5
b11000 F
b11000 P
1'
#80000
0'
#85000
b1000 .
b1000 ]
0,
b1000 B
b1000 N
b1000 Z
b1000 U
b111111111111111111111111111111000 V
b1000 D
b1000 S
b100000 6
b10 E
b10 I
b10 R
1:
1A
b1000 G
b1000 /
b101011 J
b1000000000000000100000 >
b10101100000010000000000000001000 ?
b10101100000010000000000000001000 Q
b1000000 7
b100000 5
b11100 F
b11100 P
1'
#90000
0'
#95000
b0 .
b0 ]
1,
b0 B
b0 N
b0 Z
b100100 6
b10 E
b10 I
b10 R
b0 U
b0 V
b0 D
b0 S
0:
0A
b110010 G
b110010 /
b1000 J
b1000000000000011001000 >
b100000000010000000000000110010 ?
b100000000010000000000000110010 Q
b11101100 7
b100100 5
b100000 F
b100000 P
1'
#100000
0'
#105000
b1100 .
b1100 ]
0,
b1100 B
b1100 N
b1100 Z
b1100 U
b111111111111111111111111111110100 V
b1100 D
b1100 S
b101000 6
b10 E
b10 I
b10 R
1:
1A
b1100 G
b1100 /
b101011 J
b1000000000000000110000 >
b10101100000010000000000000001100 ?
b10101100000010000000000000001100 Q
b1011000 7
b101000 5
b100100 F
b100100 P
1'
#110000
0'
#115000
b0 .
b0 ]
1,
b0 B
b0 N
b0 Z
b101100 6
b10 E
b10 I
b10 R
b0 U
b0 V
b0 D
b0 S
0:
0A
b10 G
b10 /
b1000 J
b1000000000000000001000 >
b100000000010000000000000000010 ?
b100000000010000000000000000010 Q
b110100 7
b101100 5
b101000 F
b101000 P
1'
#120000
0'
#125000
b10000 .
b10000 ]
0,
b10000 B
b10000 N
b10000 Z
b10000 U
b111111111111111111111111111110000 V
b10000 D
b10000 S
b110000 6
b10 E
b10 I
b10 R
1:
1A
b10000 G
b10000 /
b101011 J
b1000000000000001000000 >
b10101100000010000000000000010000 ?
b10101100000010000000000000010000 Q
b1110000 7
b110000 5
b101100 F
b101100 P
1'
#130000
0'
#135000
b0 .
b0 ]
1,
b0 B
b0 N
b0 Z
b110100 6
b10 E
b10 I
b10 R
b0 U
b0 V
b0 D
b0 S
0:
0A
b1 G
b1 /
b1000 J
b1000000000000000000100 >
b100000000010000000000000000001 ?
b100000000010000000000000000001 Q
b111000 7
b110100 5
b110000 F
b110000 P
1'
#140000
0'
#145000
b10100 .
b10100 ]
0,
b10100 B
b10100 N
b10100 Z
b10100 U
b111111111111111111111111111101100 V
b10100 D
b10100 S
b111000 6
b10 E
b10 I
b10 R
1:
1A
b10100 G
b10100 /
b101011 J
b1000000000000001010000 >
b10101100000010000000000000010100 ?
b10101100000010000000000000010100 Q
b10001000 7
b111000 5
b110100 F
b110100 P
1'
#150000
0'
#155000
b0 .
b0 ]
1,
b0 B
b0 N
b0 Z
b10000 -
b10000 _
b111100 6
b10 E
b10 I
b10 R
b0 U
b0 V
b0 D
b0 S
0:
0A
b0 G
b0 /
b10000 \
b1000 J
b10000000000000000000000 >
b100000000100000000000000000000 ?
b100000000100000000000000000000 Q
b111100 7
b111100 5
b111000 F
b111000 P
1'
#160000
0'
#165000
1^
b10001 -
b10001 _
b1000000 6
1=
11
1;
1A
b10001 \
b10000 [
b100011 J
b1000010001000000000000000000 >
b10001110000100010000000000000000 ?
b10001110000100010000000000000000 Q
b1000000 7
b1000000 5
b111100 F
b111100 P
1'
#170000
0'
#175000
0^
b100 -
b100 _
b1000100 6
b10 E
b10 I
b10 R
0=
01
0;
0A
b100 G
b100 /
b100 \
b1000 J
b1000000100000000000000010000 >
b100010000001000000000000000100 ?
b100010000001000000000000000100 Q
b1010100 7
b1000100 5
b1000000 F
b1000000 P
1'
#180000
0'
#185000
1^
b101 -
b101 _
b1001000 6
b10 E
b10 I
b10 R
b10 C
b10 H
b10 K
11
12
b100000 G
b10100000100000 /
b0 \
b10001 [
b0 J
b1000100000001010000010000000 >
b10001000000010100000100000 ?
b10001000000010100000100000 Q
b1010000011001000 7
b1001000 5
b1000100 F
b1000100 P
1'
#190000
0'
#195000
b11000001010000 6
b10 E
b10 I
b10 R
b0 C
b0 H
b0 K
01
02
b11111 -
b11111 _
b1001100 .
b1001100 ]
1*
b10100 G
b110000010100 /
b0 [
b11 J
b10000 0
b10000 T
b11000001010000 >
18
b1100000000000000110000010100 ?
b1100000000000000110000010100 Q
b11000010011100 7
b1001100 5
b1001000 F
b1001000 P
1'
#200000
0'
#205000
b11000001010100 6
b10 E
b10 I
b10 R
b11101 -
b11101 _
0^
0*
b110100 G
b11111111111111111111111111110100 /
b11101 \
b11101 [
b1000 J
b11111 0
b11111 T
b1110111101111111111111010000 >
08
b0 .
b0 ]
b100011101111011111111111110100 ?
b100011101111011111111111110100 Q
b11000000100100 7
b11000001010100 5
b11000001010000 F
b11000001010000 P
1'
#210000
0'
#215000
b11111 -
b11111 _
b11000001011000 6
b10 E
b10 I
b10 R
b1001100 3
b1001100 L
b1001100 `
1:
1A
b0 G
b0 /
b11111 \
b101011 J
b0 0
b0 T
b1110111111000000000000000000 >
b10101111101111110000000000000000 ?
b10101111101111110000000000000000 Q
b11000001011000 7
b11000001011000 5
b11000001010100 F
b11000001010100 P
1'
#220000
0'
#225000
b100 .
b100 ]
0,
b100 B
b100 N
b100 Z
b10000 -
b10000 _
b11000001011100 6
b10 E
b10 I
b10 R
b100 U
b111111111111111111111111111111100 V
b100 D
b100 S
b0 3
b0 L
b0 `
b100 G
b100 /
b10000 \
b1110110000000000000000010000 >
b10101111101100000000000000000100 ?
b10101111101100000000000000000100 Q
b1001100 !
b11000001101100 7
b11000001011100 5
b11000001011000 F
b11000001011000 P
1'
#230000
0'
#235000
b1000 .
b1000 ]
0,
b1000 B
b1000 N
b1000 Z
b10001 -
b10001 _
b11000001100000 6
b10 E
b10 I
b10 R
b1000 U
b111111111111111111111111111111000 V
b1000 D
b1000 S
b1000 G
b1000 /
b10001 \
b1110110001000000000000100000 >
b10101111101100010000000000001000 ?
b10101111101100010000000000001000 Q
b11000010000000 7
b11000001100000 5
b11000001011100 F
b11000001011100 P
1'
#240000
0'
#245000
b0 .
b0 ]
1^
1,
b0 B
b0 N
b0 Z
b10000 -
b10000 _
b11000001100100 6
b10 E
b10 I
b10 R
b0 U
b0 V
b0 D
b0 S
b10 C
b10 H
b10 K
11
12
0:
0A
b100000 G
b11111111111111111000000000100000 /
b0 \
b100 [
b0 J
b10000000100000000010000000 >
b100000001000000000100000 ?
b100000001000000000100000 Q
b11111111111111100011000011100100 7
b11000001100100 5
b11000001100000 F
b11000001100000 P
1'
#250000
0'
#255000
b10001 -
b10001 _
b11000001101000 6
b11111111111111111000100000100000 /
b101 [
b10100000100010000010000000 >
b101000001000100000100000 ?
b101000001000100000100000 Q
b11111111111111100101000011101000 7
b11000001101000 5
b11000001100100 F
b11000001100100 P
1'
#260000
0'
#265000
b1 -
b1 _
b11000001101100 6
b111 E
b111 I
b111 R
b101010 G
b100000101010 /
b10001 \
b0 [
b10001000010000010101000 >
b100010000100000101010 ?
b100010000100000101010 Q
b101000100010100 7
b11000001101100 5
b11000001101000 F
b11000001101000 P
1'
#270000
0'
#275000
0^
b0 -
b0 _
1+
b11000010001000 6
b110 E
b110 I
b110 R
1@
b1 C
b1 H
b1 K
01
02
b110 G
b110 /
b0 \
b1 [
b100 J
b100000000000000000011000 >
b10000001000000000000000000110 ?
b10000001000000000000000000110 Q
b11000010001000 7
b11000001110000 5
b11000001101100 F
b11000001101100 P
1'
#280000
0'
#285000
b1001100 .
b1001100 ]
1^
b11111 -
b11111 _
b1001100 <
b1001100 M
0+
b11000010001100 6
b10 E
b10 I
b10 R
b1001100 3
b1001100 L
b1001100 `
1=
11
1;
1A
b0 C
b0 H
b0 K
0@
b0 G
b0 /
b11111 \
b11101 [
b100011 J
b1110111111000000000000000000 >
b10001111101111110000000000000000 ?
b10001111101111110000000000000000 Q
b11000010001100 7
b11000010001100 5
b11000010001000 F
b11000010001000 P
1'
#290000
0'
#295000
b0 .
b0 ]
b0 <
b0 M
0,
b100 B
b100 N
b100 Z
b10000 -
b10000 _
b11000010010000 6
b10 E
b10 I
b10 R
b100 U
b111111111111111111111111111111100 V
b100 D
b100 S
b0 3
b0 L
b0 `
b100 G
b100 /
b10000 \
b1110110000000000000000010000 >
b10001111101100000000000000000100 ?
b10001111101100000000000000000100 Q
b11000010100000 7
b11000010010000 5
b11000010001100 F
b11000010001100 P
1'
#300000
0'
#305000
0,
b1000 B
b1000 N
b1000 Z
b10001 -
b10001 _
b11000010010100 6
b10 E
b10 I
b10 R
b1000 U
b111111111111111111111111111111000 V
b1000 D
b1000 S
b1000 G
b1000 /
b10001 \
b1110110001000000000000100000 >
b10001111101100010000000000001000 ?
b10001111101100010000000000001000 Q
b11000010110100 7
b11000010010100 5
b11000010010000 F
b11000010010000 P
1'
#310000
0'
#315000
0^
b0 .
b0 ]
1,
b0 B
b0 N
b0 Z
b11101 -
b11101 _
b11000010011000 6
b10 E
b10 I
b10 R
b0 U
b0 V
b0 D
b0 S
0=
01
0;
0A
b1100 G
b1100 /
b11101 \
b1000 J
b1110111101000000000000110000 >
b100011101111010000000000001100 ?
b100011101111010000000000001100 Q
b11000011001000 7
b11000010011000 5
b11000010010100 F
b11000010010100 P
1'
#320000
0'
#325000
b0 -
b0 _
b1001100 6
b0 E
b0 I
b0 R
b1001100 V
b1001100 U
b1001100 4
b1001100 W
b1001100 a
b10 C
b10 H
b10 K
11
12
1)
b1000 G
b1000 /
b0 \
b11111 [
b0 J
b1111100000000000000000100000 >
b11111000000000000000001000 ?
b11111000000000000000001000 Q
b11000010111100 7
b11000010011100 5
b11000010011000 F
b11000010011000 P
1'
#330000
0'
#335000
b11000001001100 6
b10 E
b10 I
b10 R
b0 V
b0 U
b0 4
b0 W
b0 a
b0 C
b0 H
b0 K
01
02
0)
1*
b10011 G
b110000010011 /
b0 [
b10 J
b10000 0
b10000 T
b11000001001100 >
19
b1000000000000000110000010011 ?
b1000000000000000110000010011 Q
b11000010011100 7
b1010000 5
b1001100 F
b1001100 P
1'
#340000
0'
#345000
b110000010011100 7
b11000001010000 5
b11000001001100 F
b11000001001100 P
1'
